django_database_functions/__init__.py
django_database_functions/utils.py
django_database_functions/mysql/__init__.py
django_database_functions/mysql/datetime.py
django_database_functions-0.1.dist-info/METADATA
django_database_functions-0.1.dist-info/RECORD
django_database_functions-0.1.dist-info/WHEEL
django_database_functions-0.1.dist-info/top_level.txt
