Metadata-Version: 2.1
Name: django-database-functions
Version: 0.1
Summary: Implementation of few database for Django
Home-page: https://github.com/jerinpetergeorge/django-database-functions
Author: Jerin Peter GeorgeFlying Circus
Author-email: jerinpetergeorge@gmail.com
License: MIT
Platform: UNKNOWN
